{
    "id": "medium_015",
    "name": "CV Bat",
    "difficulty": "medium",
    "width": 10,
    "height": 10,
    "solution": [
        [
            1,
            1,
            0,
            0,
            0,
            0,
            0,
            0,
            1,
            1
        ],
        [
            1,
            1,
            1,
            0,
            0,
            0,
            0,
            1,
            1,
            1
        ],
        [
            0,
            1,
            1,
            1,
            0,
            0,
            1,
            1,
            1,
            0
        ],
        [
            0,
            0,
            1,
            1,
            1,
            1,
            1,
            1,
            0,
            0
        ],
        [
            0,
            0,
            1,
            0,
            1,
            1,
            0,
            1,
            0,
            0
        ],
        [
            0,
            0,
            1,
            1,
            1,
            1,
            1,
            1,
            0,
            0
        ],
        [
            0,
            0,
            0,
            1,
            1,
            1,
            1,
            0,
            0,
            0
        ],
        [
            0,
            0,
            0,
            0,
            1,
            1,
            0,
            0,
            0,
            0
        ],
        [
            0,
            0,
            0,
            1,
            0,
            0,
            1,
            0,
            0,
            0
        ],
        [
            0,
            0,
            0,
            0,
            0,
            0,
            0,
            0,
            0,
            0
        ]
    ],
    "picture": [
        [5592405, 5592405, 0, 0, 0, 0, 0, 0, 5592405, 5592405],
        [5592405, 16711680, 5592405, 0, 0, 0, 0, 5592405, 16711680, 5592405],
        [0, 5592405, 16711680, 5592405, 0, 0, 5592405, 16711680, 5592405, 0],
        [0, 0, 5592405, 16711680, 16711680, 16711680, 16711680, 5592405, 0, 0],
        [0, 0, 5592405, 0, 16711680, 16711680, 0, 5592405, 0, 0],
        [0, 0, 5592405, 16711680, 16711680, 16711680, 16711680, 5592405, 0, 0],
        [0, 0, 0, 5592405, 16711680, 16711680, 5592405, 0, 0, 0],
        [0, 0, 0, 0, 5592405, 5592405, 0, 0, 0, 0],
        [0, 0, 0, 5592405, 0, 0, 5592405, 0, 0, 0],
        [0, 0, 0, 0, 0, 0, 0, 0, 0, 0]
    ]
}
